[
  {
    "id": "013ae54f-bc35-46e1-bf70-69a1e75af548",
    "name": "Drake",
    "birthdate": "October 24, 1986",
    "activeSince": "2001",
    "genres": ["Hip Hop", "R&B"],
    "labels": ["OVO Sound", "Republic Records"],
    "website": "https://www.drakeofficial.com/",
    "image": "https://static01.nyt.com/images/2021/12/08/arts/06drake2/06drake2-mediumSquareAt3X.jpg",
    "shortDescription": "Canadian rapper, singer, and songwriter."
  },
  {
    "id": "67b63f0b-937e-4c86-9c14-5edcb1e9c362",
    "name": "Santan Dave",
    "birthdate": "June 5, 1998",
    "activeSince": "2015",
    "genres": ["Rap", "Grime"],
    "labels": ["Neighbourhood Recordings"],
    "website": "https://www.santandave.com/",
    "image": "https://soundvenue.com/wp-content/uploads/2021/11/Dave-920x920.jpeg",
    "shortDescription": "British rapper, singer, and songwriter."
  },
  {
    "id": "4a24c7b1-41b7-4657-8ce1-41e5092e8c9c",
    "name": "Tion Wayne",
    "birthdate": "April 1, 1993",
    "activeSince": "2010",
    "genres": ["Rap", "Drill"],
    "labels": ["Atlantic Records"],
    "website": "https://www.tionwayne.com/",
    "image": "https://lastfm.freetls.fastly.net/i/u/ar0/1865f526d91d19c4d9687bb6b388addd.jpg",
    "shortDescription": "British rapper and songwriter."
  },
  {
    "id": "34b4b102-5bc7-4aeb-8d12-3a460e190c6e",
    "name": "Bugzy Malone",
    "birthdate": "December 20, 1990",
    "activeSince": "2010",
    "genres": ["Grime"],
    "labels": ["B. Somebody"],
    "website": "https://bugzymalone.co.uk/",
    "image": "https://m.media-amazon.com/images/M/MV5BZWI2MmM2ZTgtZDc5YS00MzgyLThkZjQtMmU0ZmE2M2RkNjlhXkEyXkFqcGdeQXVyMTUzMTg2ODkz._V1_.jpg",
    "shortDescription": "British grime artist and actor."
  },
  {
    "id": "a37df97d-2b05-4614-b7f3-3be9948b4f68",
    "name": "Fredo",
    "birthdate": "March 6, 1994",
    "activeSince": "2016",
    "genres": ["Rap", "Hip Hop"],
    "labels": ["Since '93", "Sony Music"],
    "website": "https://www.fredpayne.co.uk/",
    "image": "https://upload.wikimedia.org/wikipedia/commons/thumb/7/7d/Fredoin2022.jpg/640px-Fredoin2022.jpg",
    "shortDescription": "British rapper and songwriter."
  },
  {
    "name": "Lil Baby",
    "activeSince": "2017",
    "genres": "Hip Hop,Trap",
    "labels": "Quality Control,Capitol Records",
    "birthdate": "",
    "shortDescription": "American rapper, singer, and songwriter.",
    "website": "https://www.lilbabyofficial.com/",
    "image": "https://static01.nyt.com/images/2022/10/23/arts/23LIL-BABY2/23LIL-BABY2-mediumSquareAt3X.jpg",
    "id": "0f22d9d6-6f9d-4a2e-8d28-7d2047c288d1"
  },
  {
    "id": "a11aa0a7-4b3c-4f04-bc4a-9b0c5d0656a9",
    "name": "Kendrick Lamar",
    "birthdate": "June 17, 1987",
    "activeSince": "2003",
    "genres": ["Hip Hop"],
    "labels": ["Top Dawg", "Aftermath", "Interscope"],
    "website": "https://www.kendricklamar.com/",
    "image": "https://heartbeats.dk/wp-content/uploads/2019/12/kendricklamar-new.jpg",
    "shortDescription": "American rapper, songwriter, and record producer."
  },
  {
    "id": "d7c37e0f-015f-4c6c-88a0-e5f4eb1c2a97",
    "name": "J. Cole",
    "birthdate": "January 28, 1985",
    "activeSince": "2007",
    "genres": ["Hip Hop", "Rap"],
    "labels": ["Dreamville", "Roc Nation", "Interscope"],
    "website": "https://www.jcolemusic.com/",
    "image": "https://media.gq.com/photos/63c8d5a6cd63aa9138b13c7b/1:1/w_3641,h_3641,c_limit/1246142881",
    "shortDescription": "American rapper, singer, and record producer."
  },
  {
    "id": "c361635a-2b7a-46a5-8a7d-7e365ec4e035",
    "name": "Kanye West",
    "birthdate": "June 8, 1977",
    "activeSince": "1996",
    "genres": ["Hip Hop", "Rap"],
    "labels": ["GOOD Music", "Def Jam"],
    "website": "https://www.kanyewest.com/",
    "image": "https://flxt.tmsimg.com/assets/489020_v9_bc.jpg",
    "shortDescription": "American rapper, producer, and fashion designer."
  },
  {
    "id": "f0c3f8c7-72d9-4b26-af36-81b13507b131",
    "name": "Central Cee",
    "birthdate": "December 12, 1998",
    "activeSince": "2017",
    "genres": ["Rap", "UK Drill"],
    "labels": ["CCM", "Warner Records UK"],
    "website": "https://www.centralceemusic.com/",
    "image": "https://www.releaseathens.gr/wp-content/uploads/2023/03/cenral-artist.jpg",
    "shortDescription": "British rapper and songwriter."
  },
  {
    "id": "f49b93e7-8375-4c3e-8d1f-4e0e4f9f5d36",
    "name": "Akon",
    "birthdate": "April 16, 1973",
    "activeSince": "1996",
    "genres": ["R&B", "Hip Hop"],
    "labels": ["Konvict Muzik", "Universal Motown"],
    "website": "https://www.akon.com/",
    "image": "https://hips.hearstapps.com/hmg-prod/images/gettyimages-507888554.jpg",
    "shortDescription": "Senegalese-American singer, rapper, and producer."
  },
  {
    "id": "77a2a4fc-45e1-49b9-83fc-87ea2493eaa4",
    "name": "Ne-Yo",
    "birthdate": "October 18, 1979",
    "activeSince": "1994",
    "genres": ["R&B", "Pop"],
    "labels": ["Compound Entertainment", "Motown"],
    "website": "https://www.neyothegentleman.com/",
    "image": "https://azstatefair.com/wp-content/uploads/2023/03/neyo-web.-.png",
    "shortDescription": "American singer, songwriter, and actor."
  },
  {
    "id": "f0a17302-97e9-4b85-9c88-f6f237c28e93",
    "name": "Michael Jackson",
    "birthdate": "August 29, 1958",
    "activeSince": "1964",
    "genres": ["Pop", "R&B"],
    "labels": ["Epic Records", "Motown"],
    "website": "https://www.michaeljackson.com/",
    "image": "https://pbs.twimg.com/media/FMddD_mVkAAaZla?format=jpg&name=4096x4096",
    "shortDescription": "American singer, songwriter, and pop icon."
  },
  {
    "id": "cba0ca70-84ea-4cf5-a3ce-b6e5b7939e6a",
    "name": "Nelly",
    "birthdate": "November 2, 1974",
    "activeSince": "1993",
    "genres": ["Hip Hop", "R&B"],
    "labels": ["Universal Records", "Derrty Entertainment"],
    "website": "https://www.nelly.net/",
    "image": "https://cdns-images.dzcdn.net/images/artist/958412ccb4c4da8d3978ec885d0a09ef/500x500.jpg",
    "shortDescription": "American rapper, singer, and actor."
  },
  {
    "id": "d1a16f0a-0df0-4c62-a8c5-2ca713442f45",
    "name": "Lionel Richie",
    "birthdate": "June 20, 1949",
    "activeSince": "1968",
    "genres": ["Pop", "R&B"],
    "labels": ["Motown", "Mercury"],
    "website": "https://www.lionelrichie.com/",
    "image": "https://lastfm.freetls.fastly.net/i/u/ar0/251f6b43bb78fcc9d01e7cd8c20337a0.jpg",
    "shortDescription": "American singer, songwriter, and music producer."
  },
  {
    "id": "c6bdf95c-58c3-44b7-b090-6557b83774ed",
    "name": "Boyz II Men",
    "birthdate": "October 22, 1971",
    "activeSince": "1985",
    "genres": ["R&B", "Soul"],
    "labels": ["Motown", "Arista"],
    "website": "https://www.boyziimen.com/",
    "image": "https://media.vanityfair.com/photos/54caa67051062027081f1b31/master/w_2560%2Cc_limit/image.jpg",
    "shortDescription": "American R&B vocal group."
  },
  {
    "id": "eed968c4-6d9e-45e5-a7ea-d99e71f82a1a",
    "name": "R. Kelly",
    "birthdate": "January 8, 1967",
    "activeSince": "1983",
    "genres": ["R&B", "Soul"],
    "labels": ["Jive Records", "RCA Records"],
    "website": "https://www.r-kelly.com/",
    "image": "https://static01.nyt.com/images/2020/12/22/arts/22rkelly-item-2/merlin_170039889_65169358-6dab-422d-9e91-4287b61356e9-mediumSquareAt3X.jpg",
    "shortDescription": "American singer, songwriter, and record producer."
  },
  {
    "id": "8b6d9c29-7a4d-49cd-a2db-174bb29531ec",
    "name": "Usher",
    "birthdate": "October 14, 1978",
    "activeSince": "1993",
    "genres": ["R&B", "Pop"],
    "labels": ["Arista", "LaFace", "RCA Records"],
    "website": "https://www.usherworld.com/",
    "image": "https://cdn.smehost.net/2020sonymusiccouk-ukprod/wp-content/uploads/2019/10/Usher-118650661_10158777382897498_383041091290347662_o.jpg",
    "shortDescription": "American singer, songwriter, and dancer."
  },
  {
    "id": "e13f7e38-ae60-476b-a868-04129c17d8b7",
    "name": "T-Pain",
    "birthdate": "September 30, 1985",
    "activeSince": "2004",
    "genres": ["R&B", "Hip Hop"],
    "labels": ["Nappy Boy Entertainment", "RCA Records"],
    "website": "https://www.t-pain.net/",
    "image": "https://yt3.googleusercontent.com/FFp64p47zoksrnTY-ezEaZsZAMzxXuHta6hN9_NyKz__LYq7EUHp4Itvb4mtnEci5yCOOiwRYQ=s900-c-k-c0x00ffffff-no-rj",
    "shortDescription": "American rapper, singer, and record producer."
  },
  {
    "id": "3f1d26c7-7a08-4e81-83f3-86e986636791",
    "name": "Tina Turner",
    "birthdate": "November 26, 1939",
    "activeSince": "1958",
    "genres": ["Rock", "Pop", "R&B"],
    "labels": ["Capitol Records", "Parlophone"],
    "website": "https://www.tinaturnerofficial.com/",
    "image": "https://soundvenue.com/wp-content/uploads/2023/05/GettyImages-543895410-920x920.jpg",
    "shortDescription": "American-born Swiss singer, actress, and performer."
  },
  {
    "id": "83a73263-43e6-44ce-88ea-8f1f6706f7d1",
    "name": "Dionne Warwick",
    "birthdate": "December 12, 1940",
    "activeSince": "1957",
    "genres": ["R&B", "Pop", "Soul"],
    "labels": ["Scepter Records", "Warner Bros. Records"],
    "website": "https://www.dionnewarwick.info/",
    "image": "https://i.scdn.co/image/ab6761610000e5eb460f728695000dadb44a4e8c",
    "shortDescription": "American singer, actress, and television host."
  },
  {
    "id": "8f08bdef-8c90-4e57-8ca5-2b8464e6d867",
    "name": "Gladys Knight",
    "birthdate": "May 28, 1944",
    "activeSince": "1952",
    "genres": ["R&B", "Soul", "Pop"],
    "labels": ["Motown", "Buddah Records"],
    "website": "https://www.gladysknight.com/",
    "image": "https://freshairarchive.org/sites/default/files/styles/square_1600/public/2022-01/GladysKnight.jpg?itok=pZbDtWW9",
    "shortDescription": "American singer, songwriter, and actress."
  },
  {
    "id": "16e74a6b-e5c9-4d5e-9d52-8fe87aa35a53",
    "name": "Whitney Houston",
    "birthdate": "August 9, 1963",
    "activeSince": "1977",
    "genres": ["R&B", "Pop", "Soul"],
    "labels": ["Arista Records", "RCA Records"],
    "website": "https://www.whitneyhouston.com/",
    "image": "https://1265745076.rsc.cdn77.org/1024/jpg/42165-whitney-houston-whitney-LP-1-5b5051ced3de1.jpg",
    "shortDescription": "American singer, actress, and producer."
  },
  {
    "id": "f50d952d-8ee4-40b2-af41-64d905f6b19f",
    "name": "Celine Dion",
    "birthdate": "March 30, 1968",
    "activeSince": "1980",
    "genres": ["Pop", "Adult Contemporary"],
    "labels": ["Columbia Records", "Epic Records"],
    "website": "https://www.celinedion.com/",
    "image": "https://www.ok-magazin.de/sites/default/files/styles/image870w/public/2023-06/celine-dion-ernst-getty.jpg?h=cbe1fb3c",
    "shortDescription": "Canadian singer, songwriter, and businesswoman."
  },
  {
    "id": "5a6e1034-4051-47b0-82ce-936b5e9750ec",
    "name": "Mariah Carey",
    "birthdate": "March 27, 1969",
    "activeSince": "1988",
    "genres": ["Pop", "R&B", "Soul"],
    "labels": ["Columbia Records", "Epic Records"],
    "website": "https://www.mariahcarey.com/",
    "image": "https://media1.popsugar-assets.com/files/thumbor/UIpDsgzyyErbzegKlhkdvpQJOE8/fit-in/2048xorig/filters:format_auto-!!-:strip_icc-!!-/2017/08/04/692/n/1922398/53461108bc523a97_GettyImages-689747178/i/1992.jpg",
    "shortDescription": "American singer, songwriter, and actress."
  },
  {
    "id": "e89f56c2-47e6-4c5a-9d16-7d46acfd5f8e",
    "name": "Stevie Wonder",
    "birthdate": "May 13, 1950",
    "activeSince": "1961",
    "genres": ["Soul", "R&B", "Pop"],
    "labels": ["Tamla", "Motown"],
    "website": "https://www.steviewonder.net/",
    "image": "https://www.theknot.com/tk-media/images/ca152e7d-a01f-4631-9746-c51c66d211be",
    "shortDescription": "American singer, songwriter, musician, and record producer."
  },
  {
    "id": "d13a5c0e-755a-4a84-8ca5-6533c86be3f4",
    "name": "Rick Astley",
    "birthdate": "February 6, 1966",
    "activeSince": "1985",
    "genres": ["Pop", "Dance-Pop"],
    "labels": ["RCA Records"],
    "website": "https://www.rickastley.co.uk/",
    "image": "https://i.insider.com/602ee9ced3ad27001837f2ac?width=750&format=jpeg&auto=webp",
    "shortDescription": "British singer, songwriter, and musician."
  },
  {
    "id": "4d08b63c-8ea1-4b9a-8923-80d7e1e23e78",
    "name": "Elton John",
    "birthdate": "March 25, 1947",
    "activeSince": "1964",
    "genres": ["Pop", "Rock"],
    "labels": ["Rocket Records", "MCA Records"],
    "website": "https://www.eltonjohn.com/",
    "image": "https://berlingske.bmcdn.dk/media/cache/resolve/image_x_large/image/153/1531496/24047532-elton-john-returns-to-complete.jpeg",
    "shortDescription": "British singer, songwriter, and pianist."
  },
  {
    "id": "b8069ac5-88e6-4e35-89b7-97a0ecf4d7c9",
    "name": "Phil Collins",
    "birthdate": "January 30, 1951",
    "activeSince": "1968",
    "genres": ["Pop", "Rock", "Progressive Rock"],
    "labels": ["Atlantic Records", "Virgin Records"],
    "website": "https://www.philcollins.com/",
    "image": "https://m.media-amazon.com/images/M/MV5BMjY2NjU2Nzg5MV5BMl5BanBnXkFtZTYwMDUwMjg2._V1_FMjpg_UX1000_.jpg",
    "shortDescription": "English drummer, singer, songwriter, and producer."
  },
  {
    "id": "71e75827-67d4-4cb3-8f2e-1771f3e9c112",
    "name": "Earth, Wind & Fire",
    "activeSince": "1969",
    "genres": ["R&B", "Funk", "Soul", "Disco"],
    "labels": ["Columbia Records", "Legacy Recordings"],
    "website": "https://www.earthwindandfire.com/",
    "image": "https://i.scdn.co/image/ab6761610000e5eb9722e16a886767adf1178f92",
    "shortDescription": "American band known for their fusion of various music genres."
  }
]
